{"retcode":200,"data":{"version":4,"update_interval_hours":24,"settings":{"tierbase_search_timeout":15000,"mainbase_search_timeout":20000,"tierbase_api_timeout":35000,"mainbase_api_timeout":30000,"proxy_search_timeout":30000,"mirror_timeout":30000},"mainbase":["https://yazx.theology.pics","https://govz.passed-query.cc","https://hgus.county.pics","https://ixex.pleased-paxil.cc","https://ffed.shade.pics","https://yukh.driver-police.org","https://nblx.songs-editors.org","https://awdb.coated-fifty.org","https://axci.exist-pointer.net","https://vsxm.douglas-drugs.net","https://ydjx.patch-clothes.org","https://api.doneverdrop.com","https://1.4thbackupdomain.com","https://1.fifthbackupdomain.com"],"tierbase":["https://zjtl.mixture.pics:5720/h","https://eagc.egypt-value.cc:6449/h","https://dimz.kathy.pics:6360/h","https://rune.egypt-value.cc:10569/h","https://niow.induced.cc:1799/h","https://yzcw.induced.cc:5709/h","https://hmcc.induced.cc:6845/h","https://mrmo.sunday.pics:9970/h","https://ghhr.mixture.pics:3768/h","https://aqmr.kathy.pics:6658/h","https://vvjc.mixture.pics:1704/h","https://fzei.kathy.pics:3674/h","https://fkmi.induced.cc:10026/h","https://gvas.mixture.pics:10774/h","https://cxra.induced.cc:4363/h","https://xfts.kathy.pics:4427/h","https://cznl.sunday.pics:3757/h","https://eqkw.egypt-value.cc:10173/h","https://qncv.mixture.pics:5820/h","https://esvp.sunday.pics:7716/h","https://gklj.induced.cc:2716/h","https://pike.sunday.pics:9351/h","https://qrkp.kathy.pics:9277/h","https://sazs.kathy.pics:10469/h","https://juyi.mixture.pics:8062/h","https://jsae.egypt-value.cc:6440/h","https://pfjy.egypt-value.cc:2283/h","https://pzbp.kathy.pics:2024/h","https://odfo.mixture.pics:5350/h","https://ekmg.egypt-value.cc:10647/h","https://osmc.egypt-value.cc:8357/h","https://zzky.induced.cc:9921/h","https://istb.sunday.pics:3771/h","https://cqvn.mixture.pics:3702/h","https://txgq.egypt-value.cc:10678/h","https://dxmm.induced.cc:6515/h","https://gjjs.induced.cc:3350/h","https://ctrf.mixture.pics:3450/h","https://kjmw.sunday.pics:7885/h","https://dmbx.egypt-value.cc:8004/h","https://wjus.induced.cc:10913/h","https://pgtg.egypt-value.cc:10933/h","https://ruan.egypt-value.cc:2286/h","https://megj.induced.cc:7367/h","https://jdun.mixture.pics:7448/h","https://jxtt.kathy.pics:7264/h","https://vokt.mixture.pics:1540/h","https://nbaq.kathy.pics:2048/h","https://hlmn.induced.cc:4877/h","https://ozwp.mixture.pics:8416/h"],"t":1667182803951,"mirrors":["https://raw.githubusercontent.com/the7c/update/master/src/js/data.json"]}}