{"retcode":200,"data":{"version":4,"update_interval_hours":6,"settings":{"tierbase_search_timeout":15000,"mainbase_search_timeout":20000,"tierbase_api_timeout":35000,"mainbase_api_timeout":30000,"proxy_search_timeout":30000,"mirror_timeout":30000},"mainbase":["https://nblx.county.pics","https://srpx.rounds.cc","https://vsxm.rounds.cc","https://iejg.particle.pics","https://frwy.should-licence.cc","https://axci.particle.pics","https://hovd.rounds.cc","https://api.doneverdrop.com","https://1.4thbackupdomain.com","https://1.fifthbackupdomain.com","https://airmavi.com","https://airsegment.com","https://winelessons.net"],"tierbase":["https://lldi.moses-throat.cc:8281/h","https://xsbn.sunday.pics:9747/h","https://txgq.egypt-value.cc:10678/h","https://paie.moses-throat.cc:4972/h","https://zbdw.moses-throat.cc:4511/h","https://dcjc.moses-throat.cc:2240/h","https://tjlg.egypt-value.cc:3069/h","https://cuwt.debut.motorcycles:4802/h","https://aajg.vocal.pics:7321/h","https://osmc.debut.motorcycles:8357/h","https://aqmr.egypt-value.cc:6658/h","https://qrkp.sunday.pics:9277/h","https://ufes.debut.motorcycles:1319/h","https://tcab.debut.motorcycles:7677/h","https://prtl.induced.cc:6268/h","https://ezau.moses-throat.cc:10366/h","https://gnmu.egypt-value.cc:10453/h","https://siug.induced.cc:3473/h","https://knod.moses-throat.cc:4886/h","https://nvjp.debut.motorcycles:7688/h","https://satp.kathy.pics:3710/h","https://jnnm.moses-throat.cc:1249/h","https://fafv.kathy.pics:9253/h","https://zupz.induced.cc:8192/h","https://tfuf.induced.cc:3836/h","https://qjah.moses-throat.cc:1488/h","https://werl.kathy.pics:7509/h","https://islr.debut.motorcycles:4602/h","https://jsae.vocal.pics:6440/h","https://nphs.moses-throat.cc:2333/h","https://xglz.mothers.pics:8277/h","https://drgs.vocal.pics:7294/h","https://morw.moses-throat.cc:1264/h","https://wlws.mothers.pics:1097/h","https://btea.mixture.pics:7383/h","https://grvp.debut.motorcycles:10826/h","https://gpds.mixture.pics:10131/h","https://mrmo.mixture.pics:9970/h","https://lqll.debut.motorcycles:8442/h","https://idow.moses-throat.cc:8439/h","https://fzei.moses-throat.cc:3674/h","https://fcyo.moses-throat.cc:2854/h","https://ctiy.sunday.pics:8028/h","https://dxmm.moses-throat.cc:6515/h","https://hlmn.debut.motorcycles:4877/h","https://lvop.vocal.pics:1846/h","https://gebf.moses-throat.cc:3359/h","https://vjzg.debut.motorcycles:2019/h","https://fqgf.egypt-value.cc:10011/h","https://uhsm.mixture.pics:10092/h"],"t":1672077845530,"mirrors":["https://bitbucket.org/the7c/update/raw/master/ip/ens4/data.json","https://raw.githubusercontent.com/the7c/update/master/src/js/data.json"]}}