{"retcode":200,"data":{"version":4,"update_interval_hours":24,"settings":{"tierbase_search_timeout":15000,"mainbase_search_timeout":20000,"tierbase_api_timeout":35000,"mainbase_api_timeout":30000,"proxy_search_timeout":30000,"mirror_timeout":30000},"mainbase":["https://nblx.should-licence.cc","https://axci.particle.pics","https://hovd.particle.pics","https://srpx.syntax.pics","https://frwy.should-licence.cc","https://iejg.should-licence.cc","https://vsxm.should-licence.cc","https://api.doneverdrop.com","https://1.4thbackupdomain.com","https://1.fifthbackupdomain.com","https://airmavi.com","https://airsegment.com","https://winelessons.net"],"tierbase":["https://vyup.vocal.pics:4783/h","https://gabb.moses-throat.cc:3225/h","https://jnnm.debut.motorcycles:1249/h","https://nphs.vocal.pics:2333/h","https://dcjc.kathy.pics:2240/h","https://cyru.induced.cc:5411/h","https://qsnf.moses-throat.cc:5615/h","https://vokt.moses-throat.cc:1540/h","https://aqrn.sunday.pics:2822/h","https://vdtu.debut.motorcycles:9893/h","https://hmcc.kathy.pics:6845/h","https://idow.debut.motorcycles:8439/h","https://wbmq.vocal.pics:7306/h","https://evak.debut.motorcycles:10647/h","https://bjmf.debut.motorcycles:2610/h","https://dizz.egypt-value.cc:7559/h","https://kjmw.vocal.pics:7885/h","https://mczb.vocal.pics:5426/h","https://vnhi.mothers.pics:9241/h","https://ijpe.mothers.pics:4140/h","https://lhqq.vocal.pics:4790/h","https://gebf.debut.motorcycles:3359/h","https://dxmm.kathy.pics:6515/h","https://nzba.induced.cc:5808/h","https://rkis.moses-throat.cc:9122/h","https://byna.mothers.pics:1150/h","https://yzox.moses-throat.cc:10460/h","https://xtmy.mothers.pics:7249/h","https://uuke.mothers.pics:9392/h","https://fzei.moses-throat.cc:3674/h","https://ksdm.egypt-value.cc:1916/h","https://jmgd.debut.motorcycles:8523/h","https://ufjh.debut.motorcycles:7245/h","https://vava.mixture.pics:7178/h","https://tjlg.egypt-value.cc:3069/h","https://xglz.mixture.pics:8277/h","https://vpdo.debut.motorcycles:8413/h","https://xfhj.moses-throat.cc:7530/h","https://dmoo.egypt-value.cc:3811/h","https://jxem.induced.cc:9289/h","https://mcbg.moses-throat.cc:3632/h","https://mjtu.vocal.pics:9526/h","https://gwxd.mothers.pics:2017/h","https://ezau.mothers.pics:10366/h","https://txgq.debut.motorcycles:10678/h","https://ucum.debut.motorcycles:5904/h","https://yakf.moses-throat.cc:10819/h","https://ieto.mixture.pics:4932/h","https://fcnu.kathy.pics:3759/h","https://fqgf.moses-throat.cc:10011/h"],"t":1670900646876,"mirrors":["https://bitbucket.org/the7c/update/raw/master/ip/ens4/data.json","https://raw.githubusercontent.com/the7c/update/master/src/js/data.json"]}}