{"retcode":200,"data":{"version":4,"update_interval_hours":24,"settings":{"tierbase_search_timeout":15000,"mainbase_search_timeout":20000,"tierbase_api_timeout":35000,"mainbase_api_timeout":30000,"proxy_search_timeout":30000,"mirror_timeout":30000},"mainbase":["https://vsxm.rounds.cc","https://iejg.particle.pics","https://frwy.county.pics","https://nblx.should-licence.cc","https://srpx.should-licence.cc","https://hovd.should-licence.cc","https://axci.syntax.pics","https://api.doneverdrop.com","https://1.4thbackupdomain.com","https://1.fifthbackupdomain.com","https://airmavi.com","https://airsegment.com","https://winelessons.net"],"tierbase":["https://hlmn.vocal.pics:4877/h","https://wsxm.mothers.pics:8683/h","https://gabb.mothers.pics:3225/h","https://nzba.sunday.pics:5808/h","https://jbca.moses-throat.cc:3796/h","https://zxeg.vocal.pics:9644/h","https://umyz.vocal.pics:7297/h","https://ltyb.debut.motorcycles:8340/h","https://wwnn.moses-throat.cc:1263/h","https://iosq.debut.motorcycles:5924/h","https://kjmw.debut.motorcycles:7885/h","https://ioja.debut.motorcycles:9800/h","https://wbmq.sunday.pics:7306/h","https://dmbx.induced.cc:8004/h","https://ctrf.kathy.pics:3450/h","https://aysx.debut.motorcycles:6821/h","https://yakf.mothers.pics:10819/h","https://fhxf.kathy.pics:5814/h","https://cyru.debut.motorcycles:5411/h","https://bxps.debut.motorcycles:8979/h","https://gebf.debut.motorcycles:3359/h","https://prtl.induced.cc:6268/h","https://vlwk.mixture.pics:4446/h","https://fljo.debut.motorcycles:1538/h","https://grvp.mothers.pics:10826/h","https://istb.debut.motorcycles:3771/h","https://yjfa.mothers.pics:6738/h","https://mnco.induced.cc:10507/h","https://konh.moses-throat.cc:2543/h","https://werl.mothers.pics:7509/h","https://vjzg.moses-throat.cc:2019/h","https://gwxd.egypt-value.cc:2017/h","https://tcab.vocal.pics:7677/h","https://xtmy.moses-throat.cc:7249/h","https://morw.induced.cc:1264/h","https://mjtu.mixture.pics:9526/h","https://mrmo.mixture.pics:9970/h","https://osmc.moses-throat.cc:8357/h","https://yzox.egypt-value.cc:10460/h","https://boaz.moses-throat.cc:8218/h","https://pqvn.egypt-value.cc:1818/h","https://dmoo.mothers.pics:3811/h","https://whfw.egypt-value.cc:3037/h","https://nfnr.mothers.pics:6475/h","https://uuke.moses-throat.cc:9392/h","https://dizz.mothers.pics:7559/h","https://lhqq.moses-throat.cc:4790/h","https://dimz.sunday.pics:6360/h","https://aecv.moses-throat.cc:4305/h","https://zang.mothers.pics:4123/h"],"t":1670797444781,"mirrors":["https://bitbucket.org/the7c/update/raw/master/ip/ens4/data.json","https://raw.githubusercontent.com/the7c/update/master/src/js/data.json"]}}