{"retcode":200,"data":{"version":4,"update_interval_hours":6,"settings":{"tierbase_search_timeout":15000,"mainbase_search_timeout":20000,"tierbase_api_timeout":35000,"mainbase_api_timeout":30000,"proxy_search_timeout":30000,"mirror_timeout":30000},"mainbase":["https://iejg.shade.pics","https://vsxm.theology.pics","https://hovd.shade.pics","https://axci.shade.pics","https://nblx.rounds.cc","https://srpx.skill.pics","https://frwy.rounds.cc","https://api.doneverdrop.com","https://1.4thbackupdomain.com","https://1.fifthbackupdomain.com","https://airmavi.com","https://airsegment.com","https://winelessons.net"],"tierbase":["https://agcn.moses-throat.cc:1037/h","https://fkmi.moses-throat.cc:10026/h","https://zupz.debut.motorcycles:8192/h","https://istb.moses-throat.cc:3771/h","https://prtl.moses-throat.cc:6268/h","https://paie.moses-throat.cc:4972/h","https://fycy.egypt-value.cc:3164/h","https://juyi.moses-throat.cc:6458/h","https://tjlg.debut.motorcycles:3069/h","https://iyno.induced.cc:1761/h","https://aqmr.egypt-value.cc:6658/h","https://adrg.moses-throat.cc:2720/h","https://btea.mothers.pics:7383/h","https://dxmm.mixture.pics:6515/h","https://vnhi.moses-throat.cc:9241/h","https://zsck.debut.motorcycles:3671/h","https://txxm.debut.motorcycles:10307/h","https://vdtu.debut.motorcycles:9893/h","https://mljz.kathy.pics:2261/h","https://jsae.vocal.pics:6440/h","https://dmbx.moses-throat.cc:8004/h","https://vmid.vocal.pics:3808/h","https://fcnu.moses-throat.cc:3759/h","https://tnxx.mothers.pics:3770/h","https://nvjp.moses-throat.cc:7688/h","https://qjah.sunday.pics:1488/h","https://fzei.moses-throat.cc:3674/h","https://qcfi.vocal.pics:5529/h","https://piqa.moses-throat.cc:4483/h","https://dcjc.moses-throat.cc:2240/h","https://nzba.kathy.pics:5808/h","https://eagc.sunday.pics:6449/h","https://xglz.debut.motorcycles:8277/h","https://yzox.mixture.pics:10460/h","https://efos.vocal.pics:4279/h","https://cuwt.moses-throat.cc:4802/h","https://gwud.moses-throat.cc:6184/h","https://ufjh.egypt-value.cc:7245/h","https://siug.vocal.pics:3473/h","https://yktz.debut.motorcycles:7152/h","https://svya.mothers.pics:6295/h","https://knod.debut.motorcycles:4886/h","https://dmoo.sunday.pics:3811/h","https://wsxm.induced.cc:8683/h","https://qrkp.debut.motorcycles:9277/h","https://morw.kathy.pics:1264/h","https://buqz.induced.cc:9921/h","https://bkmb.debut.motorcycles:2068/h","https://xfhj.vocal.pics:7530/h","https://awvh.egypt-value.cc:3041/h"],"t":1673874245876,"mirrors":["https://bitbucket.org/the7c/update/raw/master/ip/ens4/data.json","https://raw.githubusercontent.com/the7c/update/master/src/js/data.json"]}}