{"retcode":200,"data":{"version":4,"update_interval_hours":6,"settings":{"tierbase_search_timeout":15000,"mainbase_search_timeout":20000,"tierbase_api_timeout":35000,"mainbase_api_timeout":30000,"proxy_search_timeout":30000,"mirror_timeout":30000},"mainbase":["https://nblx.rounds.cc","https://iejg.shade.pics","https://frwy.passed-query.cc","https://axci.rounds.cc","https://hovd.theology.pics","https://srpx.shade.pics","https://vsxm.particle.pics","https://api.doneverdrop.com","https://1.4thbackupdomain.com","https://1.fifthbackupdomain.com","https://airmavi.com","https://airsegment.com","https://winelessons.net"],"tierbase":["https://jmgd.mothers.pics:8523/h","https://vava.debut.motorcycles:7178/h","https://txgq.sunday.pics:10678/h","https://zang.mothers.pics:4123/h","https://exnk.vocal.pics:3382/h","https://morw.moses-throat.cc:1264/h","https://ltyb.debut.motorcycles:8340/h","https://hlmn.moses-throat.cc:4877/h","https://umyz.mothers.pics:7297/h","https://gpds.sunday.pics:10131/h","https://qjah.moses-throat.cc:1488/h","https://vkzr.induced.cc:9951/h","https://nvjp.kathy.pics:7688/h","https://mcbg.debut.motorcycles:3632/h","https://nzba.debut.motorcycles:5808/h","https://jxem.moses-throat.cc:9289/h","https://bznu.moses-throat.cc:4565/h","https://lvop.moses-throat.cc:1846/h","https://ezau.moses-throat.cc:10366/h","https://fkmi.moses-throat.cc:10026/h","https://osmc.moses-throat.cc:8357/h","https://qvqc.egypt-value.cc:5137/h","https://fljo.moses-throat.cc:1538/h","https://aqrn.mothers.pics:2822/h","https://dxmm.mothers.pics:6515/h","https://ioja.induced.cc:9800/h","https://bxps.debut.motorcycles:8979/h","https://dmoo.egypt-value.cc:3811/h","https://bkmb.kathy.pics:2068/h","https://siug.moses-throat.cc:3473/h","https://vdtu.kathy.pics:9893/h","https://istb.moses-throat.cc:3771/h","https://tcab.moses-throat.cc:7677/h","https://dimz.moses-throat.cc:6360/h","https://yjfa.debut.motorcycles:6738/h","https://tnxx.kathy.pics:3770/h","https://sfmc.moses-throat.cc:6393/h","https://fafv.debut.motorcycles:9253/h","https://xbtw.moses-throat.cc:3194/h","https://yktz.vocal.pics:7152/h","https://aysx.moses-throat.cc:6821/h","https://piqa.sunday.pics:4483/h","https://lhqq.moses-throat.cc:4790/h","https://lqll.debut.motorcycles:8442/h","https://ctiy.moses-throat.cc:8028/h","https://efos.mixture.pics:4279/h","https://zxeg.sunday.pics:9644/h","https://btea.moses-throat.cc:7383/h","https://tfuf.moses-throat.cc:3836/h","https://xglz.moses-throat.cc:8277/h"],"t":1672183445499,"mirrors":["https://bitbucket.org/the7c/update/raw/master/ip/ens4/data.json","https://raw.githubusercontent.com/the7c/update/master/src/js/data.json"]}}