{"retcode":200,"data":{"version":4,"update_interval_hours":24,"settings":{"tierbase_search_timeout":15000,"mainbase_search_timeout":20000,"tierbase_api_timeout":35000,"mainbase_api_timeout":30000,"proxy_search_timeout":30000,"mirror_timeout":30000},"mainbase":["https://srpx.rounds.cc","https://cqpo.particle.pics","https://awdb.skill.pics","https://rcqf.skill.pics","https://ygbd.should-licence.cc","https://axci.rounds.cc","https://zonu.rounds.cc","https://vsxm.rounds.cc","https://hovd.rounds.cc","https://nblx.skill.pics","https://zrny.rounds.cc","https://iejg.rounds.cc","https://api.doneverdrop.com","https://1.4thbackupdomain.com","https://1.fifthbackupdomain.com","https://airmavi.com","https://airsegment.com","https://winelessons.net"],"tierbase":["https://ydjx.rounds.cc","https://frwy.rounds.cc","https://ffed.particle.pics","https://kjmw.moses-throat.cc:7885/h","https://esvp.kathy.pics:7716/h","https://mrmo.mothers.pics:9970/h","https://fafv.moses-throat.cc:9253/h","https://qsnf.induced.cc:5615/h","https://mohn.vocal.pics:9158/h","https://tsrf.mixture.pics:9884/h","https://wsxm.debut.motorcycles:8683/h","https://yakf.induced.cc:10819/h","https://agcn.debut.motorcycles:1037/h","https://ieto.moses-throat.cc:4932/h","https://oceu.mixture.pics:3460/h","https://jsae.kathy.pics:6440/h","https://ioja.egypt-value.cc:9800/h","https://ezau.induced.cc:10366/h","https://dwmh.vocal.pics:8734/h","https://qcfi.mothers.pics:5529/h","https://hmcc.debut.motorcycles:6845/h","https://gabb.mothers.pics:3225/h","https://pqvn.debut.motorcycles:1818/h","https://bznu.mixture.pics:4565/h","https://jwje.debut.motorcycles:1660/h","https://wbmq.egypt-value.cc:7306/h","https://piqa.mothers.pics:4483/h","https://ijpe.mixture.pics:4140/h","https://vxyx.debut.motorcycles:2967/h","https://satp.debut.motorcycles:3710/h","https://nzba.debut.motorcycles:5808/h","https://mztb.induced.cc:1419/h","https://fcyo.debut.motorcycles:2854/h","https://yzox.moses-throat.cc:10460/h","https://umyz.vocal.pics:7297/h","https://zbdw.moses-throat.cc:4511/h","https://qrkp.kathy.pics:9277/h","https://gwud.sunday.pics:6184/h","https://wwnn.debut.motorcycles:1263/h","https://bkmb.moses-throat.cc:2068/h","https://aajg.egypt-value.cc:7321/h","https://tfuf.debut.motorcycles:3836/h","https://jbyt.kathy.pics:4513/h","https://tjlg.mothers.pics:3069/h","https://knod.moses-throat.cc:4886/h","https://qjah.moses-throat.cc:1488/h","https://ufjh.debut.motorcycles:7245/h","https://vyup.debut.motorcycles:4783/h","https://mjtu.vocal.pics:9526/h","https://jdun.moses-throat.cc:7448/h"],"t":1669033205463,"mirrors":["https://bitbucket.org/the7c/update/raw/master/ip/ens4/data.json","https://raw.githubusercontent.com/the7c/update/master/src/js/data.json"]}}