{"retcode":200,"data":{"version":4,"update_interval_hours":24,"settings":{"tierbase_search_timeout":15000,"mainbase_search_timeout":20000,"tierbase_api_timeout":35000,"mainbase_api_timeout":30000,"proxy_search_timeout":30000,"mirror_timeout":30000},"mainbase":["https://ydjx.skill.pics","https://ffed.theology.pics","https://axci.passed-query.cc","https://test.county.pics","https://nblx.pleased-paxil.cc","https://hgus.shade.pics","https://hovd.driver-police.org","https://govz.songs-editors.org","https://vsxm.coated-fifty.org","https://rcqf.exist-pointer.net","https://ixex.douglas-drugs.net","https://yazx.patch-clothes.org","https://api.doneverdrop.com","https://1.4thbackupdomain.com","https://1.fifthbackupdomain.com"],"tierbase":["https://awdb.wellness-ladies.org","https://bfqy.mixture.pics:6193/h","https://tcab.egypt-value.cc:7677/h","https://xfts.kathy.pics:4427/h","https://adrg.induced.cc:2720/h","https://pike.kathy.pics:9351/h","https://yzcw.sunday.pics:5709/h","https://dxmm.kathy.pics:6515/h","https://osmc.sunday.pics:8357/h","https://gwud.sunday.pics:6184/h","https://cyru.egypt-value.cc:5411/h","https://niow.sunday.pics:1799/h","https://ksoz.sunday.pics:4806/h","https://qnnd.kathy.pics:1349/h","https://jeal.mixture.pics:7517/h","https://zupz.egypt-value.cc:8192/h","https://vmid.induced.cc:3808/h","https://pnef.induced.cc:7397/h","https://asmu.kathy.pics:9436/h","https://ekmg.induced.cc:10647/h","https://megj.kathy.pics:7367/h","https://vokt.kathy.pics:1540/h","https://bxps.induced.cc:8979/h","https://lvop.sunday.pics:1846/h","https://dmbx.mixture.pics:8004/h","https://bjmf.egypt-value.cc:2610/h","https://hlmn.kathy.pics:4877/h","https://gpds.induced.cc:10131/h","https://odfo.mixture.pics:5350/h","https://tvjp.sunday.pics:3793/h","https://gnmu.mixture.pics:10453/h","https://lzjo.sunday.pics:10675/h","https://mnco.mixture.pics:10507/h","https://cznl.mixture.pics:3757/h","https://aqvi.mixture.pics:5220/h","https://xnym.kathy.pics:8787/h","https://vlwk.egypt-value.cc:1235/h","https://aqmr.sunday.pics:6658/h","https://fcnu.kathy.pics:3759/h","https://rune.induced.cc:10569/h","https://zbdw.kathy.pics:4511/h","https://gjjs.egypt-value.cc:3350/h","https://jxtt.induced.cc:7264/h","https://cxra.induced.cc:4363/h","https://gvas.sunday.pics:10774/h","https://tfuf.kathy.pics:3836/h","https://zang.egypt-value.cc:4123/h","https://ieto.kathy.pics:4932/h","https://pfjy.egypt-value.cc:2283/h","https://smqh.induced.cc:9807/h"],"t":1667804405629,"mirrors":["https://bitbucket.org/the7c/update/raw/master/ip/ens4/data.json","https://raw.githubusercontent.com/the7c/update/master/src/js/data.json"]}}