{"retcode":200,"data":{"version":4,"update_interval_hours":24,"settings":{"tierbase_search_timeout":15000,"mainbase_search_timeout":20000,"tierbase_api_timeout":35000,"mainbase_api_timeout":30000,"proxy_search_timeout":30000,"mirror_timeout":30000},"mainbase":["https://hovd.rounds.cc","https://vsxm.skill.pics","https://nblx.should-licence.cc","https://iejg.passed-query.cc","https://frwy.pleased-paxil.cc","https://srpx.should-licence.cc","https://axci.should-licence.cc","https://api.doneverdrop.com","https://1.4thbackupdomain.com","https://1.fifthbackupdomain.com","https://airmavi.com","https://airsegment.com","https://winelessons.net"],"tierbase":["https://fcnu.moses-throat.cc:3759/h","https://piqa.mixture.pics:4483/h","https://qsnf.egypt-value.cc:5615/h","https://vnhi.sunday.pics:9241/h","https://niow.sunday.pics:1799/h","https://fuvb.moses-throat.cc:10851/h","https://vjzg.moses-throat.cc:2019/h","https://siug.moses-throat.cc:3473/h","https://aecv.sunday.pics:4305/h","https://khzk.debut.motorcycles:7665/h","https://zxeg.debut.motorcycles:9644/h","https://rbvh.debut.motorcycles:4432/h","https://nphs.moses-throat.cc:2333/h","https://zupz.sunday.pics:8192/h","https://ioja.moses-throat.cc:9800/h","https://boaz.vocal.pics:8218/h","https://drgs.debut.motorcycles:7294/h","https://konh.egypt-value.cc:2543/h","https://werl.sunday.pics:7509/h","https://agcn.moses-throat.cc:1037/h","https://gwxd.moses-throat.cc:2017/h","https://dmoo.debut.motorcycles:3811/h","https://ctrf.egypt-value.cc:3450/h","https://uuke.moses-throat.cc:9392/h","https://ufjh.induced.cc:7245/h","https://gebf.sunday.pics:3359/h","https://fkmi.kathy.pics:10026/h","https://aysx.vocal.pics:6821/h","https://kjmw.mixture.pics:7885/h","https://zbdw.induced.cc:4511/h","https://jsae.vocal.pics:6440/h","https://qvqc.sunday.pics:5137/h","https://nzba.vocal.pics:5808/h","https://istb.vocal.pics:3771/h","https://buqz.debut.motorcycles:9921/h","https://zang.sunday.pics:4123/h","https://exnk.vocal.pics:3382/h","https://fafv.vocal.pics:9253/h","https://eagc.vocal.pics:6449/h","https://gpds.sunday.pics:10131/h","https://prtl.induced.cc:6268/h","https://radk.moses-throat.cc:8450/h","https://ieto.debut.motorcycles:4932/h","https://rune.moses-throat.cc:10569/h","https://pqvn.vocal.pics:1818/h","https://wlws.moses-throat.cc:1097/h","https://hkld.moses-throat.cc:9184/h","https://tcab.vocal.pics:7677/h","https://esvp.mixture.pics:7716/h","https://smqh.debut.motorcycles:9807/h"],"t":1669583045085,"mirrors":["https://bitbucket.org/the7c/update/raw/master/ip/ens4/data.json","https://raw.githubusercontent.com/the7c/update/master/src/js/data.json"]}}