{"retcode":200,"data":{"version":4,"update_interval_hours":6,"settings":{"tierbase_search_timeout":15000,"mainbase_search_timeout":20000,"tierbase_api_timeout":35000,"mainbase_api_timeout":30000,"proxy_search_timeout":30000,"mirror_timeout":30000},"mainbase":["https://iejg.should-licence.cc","https://nblx.rounds.cc","https://hovd.particle.pics","https://srpx.syntax.pics","https://vsxm.rounds.cc","https://axci.theology.pics","https://frwy.passed-query.cc","https://api.doneverdrop.com","https://1.4thbackupdomain.com","https://1.fifthbackupdomain.com","https://airmavi.com","https://airsegment.com","https://winelessons.net"],"tierbase":["https://ctrf.sunday.pics:3450/h","https://yzox.kathy.pics:10460/h","https://zbdw.vocal.pics:4511/h","https://islr.kathy.pics:4602/h","https://uhsm.mixture.pics:10092/h","https://vjzg.vocal.pics:2019/h","https://dimz.egypt-value.cc:6360/h","https://satp.egypt-value.cc:3710/h","https://dasr.debut.motorcycles:2210/h","https://lldi.moses-throat.cc:8281/h","https://xfhj.moses-throat.cc:7530/h","https://ltyb.sunday.pics:8340/h","https://mcbg.induced.cc:3632/h","https://vmid.induced.cc:3808/h","https://qjah.sunday.pics:1488/h","https://dxmm.moses-throat.cc:6515/h","https://rwih.debut.motorcycles:2020/h","https://ozwp.moses-throat.cc:8416/h","https://tfuf.vocal.pics:3836/h","https://dmoo.moses-throat.cc:3811/h","https://zang.moses-throat.cc:4123/h","https://rune.vocal.pics:10569/h","https://zupz.induced.cc:8192/h","https://qrkp.egypt-value.cc:9277/h","https://tjlg.moses-throat.cc:3069/h","https://cyru.moses-throat.cc:5411/h","https://ufes.induced.cc:1319/h","https://smqh.debut.motorcycles:9807/h","https://fzei.moses-throat.cc:3674/h","https://gmsk.moses-throat.cc:7066/h","https://jnnm.debut.motorcycles:1249/h","https://mrmo.egypt-value.cc:9970/h","https://lfnn.induced.cc:6267/h","https://gebf.egypt-value.cc:3359/h","https://fhxf.vocal.pics:5814/h","https://vokt.induced.cc:1540/h","https://hkld.moses-throat.cc:9184/h","https://radk.sunday.pics:8450/h","https://jwje.mothers.pics:1660/h","https://aajg.kathy.pics:7321/h","https://yjfa.mixture.pics:6738/h","https://kjmw.mixture.pics:7885/h","https://pqvn.sunday.pics:1818/h","https://knod.mothers.pics:4886/h","https://drgs.moses-throat.cc:7294/h","https://umyz.moses-throat.cc:7297/h","https://siug.sunday.pics:3473/h","https://jdun.debut.motorcycles:7448/h","https://mjtu.mixture.pics:9526/h","https://sfmc.sunday.pics:6393/h"],"t":1671042245040,"mirrors":["https://bitbucket.org/the7c/update/raw/master/ip/ens4/data.json","https://raw.githubusercontent.com/the7c/update/master/src/js/data.json"]}}