{"retcode":200,"data":{"version":4,"update_interval_hours":6,"settings":{"tierbase_search_timeout":15000,"mainbase_search_timeout":20000,"tierbase_api_timeout":35000,"mainbase_api_timeout":30000,"proxy_search_timeout":30000,"mirror_timeout":30000},"mainbase":["https://hovd.particle.pics","https://axci.particle.pics","https://frwy.particle.pics","https://srpx.particle.pics","https://nblx.should-licence.cc","https://iejg.rounds.cc","https://vsxm.pleased-paxil.cc","https://api.doneverdrop.com","https://1.4thbackupdomain.com","https://1.fifthbackupdomain.com","https://airmavi.com","https://airsegment.com","https://winelessons.net"],"tierbase":["https://paie.moses-throat.cc:4972/h","https://aecv.egypt-value.cc:4305/h","https://fljo.egypt-value.cc:1538/h","https://islr.moses-throat.cc:4602/h","https://grvp.moses-throat.cc:10826/h","https://mrmo.sunday.pics:9970/h","https://zang.mothers.pics:4123/h","https://bjmf.debut.motorcycles:2610/h","https://niow.moses-throat.cc:1799/h","https://piqa.moses-throat.cc:4483/h","https://gwxd.moses-throat.cc:2017/h","https://satp.moses-throat.cc:3710/h","https://fkmi.mixture.pics:10026/h","https://hkld.mothers.pics:9184/h","https://gwud.debut.motorcycles:6184/h","https://mnco.sunday.pics:10507/h","https://prtl.moses-throat.cc:6268/h","https://euli.moses-throat.cc:4793/h","https://txgq.moses-throat.cc:10678/h","https://eagc.egypt-value.cc:6449/h","https://gabb.vocal.pics:3225/h","https://cyru.moses-throat.cc:5411/h","https://dmoo.moses-throat.cc:3811/h","https://fafv.moses-throat.cc:9253/h","https://rune.vocal.pics:10569/h","https://wbmq.induced.cc:7306/h","https://nphs.moses-throat.cc:2333/h","https://qvqc.moses-throat.cc:5137/h","https://ezau.sunday.pics:10366/h","https://dizz.moses-throat.cc:3007/h","https://ctrf.mixture.pics:3450/h","https://iosq.sunday.pics:1876/h","https://qsnf.egypt-value.cc:5615/h","https://nqbn.vocal.pics:3036/h","https://osmc.induced.cc:8357/h","https://zyqi.moses-throat.cc:7170/h","https://owcn.mixture.pics:2340/h","https://bxps.debut.motorcycles:8979/h","https://vpdo.debut.motorcycles:8413/h","https://nzba.moses-throat.cc:5808/h","https://qcfi.moses-throat.cc:5529/h","https://gebf.induced.cc:3359/h","https://cdyk.induced.cc:5730/h","https://bgzp.mothers.pics:8023/h","https://cpzq.debut.motorcycles:2395/h","https://hlmn.vocal.pics:4877/h","https://dixf.moses-throat.cc:8548/h","https://zxeg.mothers.pics:9644/h","https://xbtw.moses-throat.cc:3194/h","https://tcab.egypt-value.cc:7677/h"],"t":1674676806101,"mirrors":["https://bitbucket.org/the7c/update/raw/master/ip/ens4/data.json","https://raw.githubusercontent.com/the7c/update/master/src/js/data.json"]}}