{"retcode":200,"data":{"version":4,"update_interval_hours":24,"settings":{"tierbase_search_timeout":15000,"mainbase_search_timeout":20000,"tierbase_api_timeout":35000,"mainbase_api_timeout":30000,"proxy_search_timeout":30000,"mirror_timeout":30000},"mainbase":["https://vezk.anyway-teens.cc","https://ozgu.anyway-teens.cc","https://myyw.dishes.cc","https://hkkp.burden-chris.cc","https://yazx.anyway-teens.cc","https://iqvm.burden-chris.cc","https://tbft.anyway-teens.cc","https://ixex.worlds.pics","https://mrmh.burden-chris.cc","https://api.keepthisdomain.com","https://1.4thbackupdomain.com","https://1.fifthbackupdomain.com","https://airmavi.com","https://airsegment.com","https://winelessons.net"],"tierbase":["https://ytfk.quote-dayton.xyz:10737/s","https://mpmy.dealt.cc:6989/s","https://otzk.purposes-blink.cc:3123/s","https://gcll.triangle.pics:8618/s","https://ioet.bytes.motorcycles:7464/s","https://suiq.turns.motorcycles:7360/s","https://mljz.quote-dayton.xyz:2351/s","https://cfww.dealt.cc:7625/s","https://umwn.quote-dayton.xyz:6719/s","https://hjne.turns.motorcycles:2574/s","https://iank.turns.motorcycles:3509/s","https://ulps.quote-dayton.xyz:10079/s","https://tznu.plugins.pics:7687/s","https://elhu.bytes.motorcycles:4763/s","https://gflf.quote-dayton.xyz:8376/s","https://amjb.plugins.pics:10073/s","https://pgpf.purposes-blink.cc:9728/s","https://wwmt.turns.motorcycles:8807/s","https://qyqw.purposes-blink.cc:2872/s","https://vjuu.bytes.motorcycles:9194/s","https://yige.bytes.motorcycles:5946/s","https://cyxh.fraud.pics:1519/s","https://tbeh.purposes-blink.cc:3806/s","https://aksj.purposes-blink.cc:3469/s","https://qthb.dealt.cc:5848/s","https://hejh.fraud.pics:8229/s","https://ujxa.bytes.motorcycles:4956/s","https://mkjg.dealt.cc:5352/s","https://drpg.assuming.cc:10640/s","https://cbke.fraud.pics:8117/s","https://elbn.plugins.pics:3249/s","https://dkfj.purposes-blink.cc:4121/s","https://gyhx.turns.motorcycles:3679/s","https://vgfz.plugins.pics:2528/s","https://uonk.turns.motorcycles:7793/s","https://geiu.quote-dayton.xyz:4846/s","https://qgyh.purposes-blink.cc:10674/s","https://dvvd.quote-dayton.xyz:7242/s","https://qcal.turns.motorcycles:2392/s","https://ssnv.fraud.pics:6761/s","https://uwzo.quote-dayton.xyz:8943/s","https://buhr.assuming.cc:8905/s","https://wbts.purposes-blink.cc:10591/s","https://aesy.turns.motorcycles:2517/s","https://ybzv.bytes.motorcycles:5276/s","https://wjeu.quote-dayton.xyz:9064/s","https://ujen.bytes.motorcycles:8063/s","https://jzci.turns.motorcycles:1210/s","https://peir.fraud.pics:10078/s","https://kvrz.purposes-blink.cc:7128/s"],"t":1670044923294,"mirrors":["https://bitbucket.org/the7c/update/raw/master/edge/pub/data.json","https://raw.githubusercontent.com/the7c/update/master/master/ui/data.json"]}}