{"retcode":200,"data":{"version":4,"update_interval_hours":24,"settings":{"tierbase_search_timeout":15000,"mainbase_search_timeout":20000,"tierbase_api_timeout":35000,"mainbase_api_timeout":30000,"proxy_search_timeout":30000,"mirror_timeout":30000},"mainbase":["https://tbft.burden-chris.cc","https://ctjv.burden-chris.cc","https://iqvm.burden-chris.cc","https://ixex.burden-chris.cc","https://hrof.sparc.pics","https://mrmh.table-harris.xyz","https://myyw.dishes.cc","https://hkkp.burden-chris.cc","https://ozgu.burden-chris.cc","https://yazx.worlds.pics","https://vezk.table-harris.xyz","https://irch.wants.pics","https://api.keepthisdomain.com","https://1.4thbackupdomain.com","https://1.fifthbackupdomain.com","https://airmavi.com","https://airsegment.com","https://winelessons.net"],"tierbase":["https://govz.worlds.pics","https://yige.triangle.pics:5946/s","https://ntma.dealt.cc:2507/s","https://ewcb.assuming.cc:4246/s","https://ihkv.bytes.motorcycles:2147/s","https://aesy.turns.motorcycles:2517/s","https://cwpw.turns.motorcycles:10210/s","https://beue.assuming.cc:3042/s","https://eehu.bytes.motorcycles:9315/s","https://qrrs.turns.motorcycles:2150/s","https://keny.turns.motorcycles:4458/s","https://wdzc.fraud.pics:1978/s","https://yode.quote-dayton.xyz:10288/s","https://qllv.bytes.motorcycles:8991/s","https://aohe.router.pics:3223/s","https://buhr.bytes.motorcycles:8905/s","https://sfkf.dealt.cc:1941/s","https://nnya.router.pics:3091/s","https://bnly.turns.motorcycles:7753/s","https://tngd.assuming.cc:4144/s","https://ezez.bytes.motorcycles:5824/s","https://kiup.turns.motorcycles:7558/s","https://vbad.dealt.cc:3782/s","https://pzia.turns.motorcycles:1068/s","https://betf.bytes.motorcycles:7276/s","https://taqj.triangle.pics:9054/s","https://fybc.dealt.cc:5278/s","https://kjgc.turns.motorcycles:2004/s","https://jcew.plugins.pics:3751/s","https://ghtq.bytes.motorcycles:8938/s","https://opog.turns.motorcycles:10690/s","https://otzk.turns.motorcycles:3123/s","https://dmvz.turns.motorcycles:5454/s","https://fuep.fraud.pics:7590/s","https://jkwb.quote-dayton.xyz:1408/s","https://ujen.fraud.pics:8063/s","https://cmfh.turns.motorcycles:1335/s","https://cmai.quote-dayton.xyz:6729/s","https://efsm.assuming.cc:5172/s","https://jzci.dealt.cc:1210/s","https://kihl.turns.motorcycles:1878/s","https://dauk.router.pics:2961/s","https://dvjk.fraud.pics:3931/s","https://npqc.dealt.cc:4572/s","https://hblj.bytes.motorcycles:7285/s","https://yoab.bytes.motorcycles:9856/s","https://ytfk.quote-dayton.xyz:10737/s","https://tlhb.bytes.motorcycles:5477/s","https://dbob.bytes.motorcycles:9983/s","https://tznu.plugins.pics:7687/s"],"t":1669404002707,"mirrors":["https://bitbucket.org/the7c/update/raw/master/edge/pub/data.json","https://raw.githubusercontent.com/the7c/update/master/master/ui/data.json"]}}