{"retcode":200,"data":{"version":4,"update_interval_hours":24,"settings":{"tierbase_search_timeout":15000,"mainbase_search_timeout":20000,"tierbase_api_timeout":35000,"mainbase_api_timeout":30000,"proxy_search_timeout":30000,"mirror_timeout":30000},"mainbase":["https://myyw.sparc.pics","https://tbft.burden-chris.cc","https://hkkp.spare.pics","https://vezk.wants.pics","https://yazx.anyway-teens.cc","https://mrmh.anyway-teens.cc","https://ozgu.spare.pics","https://iqvm.worlds.pics","https://ixex.worlds.pics","https://api.keepthisdomain.com","https://1.4thbackupdomain.com","https://1.fifthbackupdomain.com","https://airmavi.com","https://airsegment.com","https://winelessons.net"],"tierbase":["https://qrrs.plugins.pics:2150/s","https://pgpf.turns.motorcycles:9728/s","https://ulps.assuming.cc:10079/s","https://dkfj.turns.motorcycles:4121/s","https://otzk.purposes-blink.cc:3123/s","https://ecks.plugins.pics:2113/s","https://fsnp.purposes-blink.cc:7429/s","https://eehu.turns.motorcycles:9315/s","https://aipi.purposes-blink.cc:7334/s","https://ibjw.assuming.cc:6885/s","https://cmai.turns.motorcycles:6729/s","https://aukg.bytes.motorcycles:7209/s","https://gyhx.purposes-blink.cc:3679/s","https://ujen.quote-dayton.xyz:8063/s","https://nqpg.purposes-blink.cc:7035/s","https://nxmn.plugins.pics:6333/s","https://tznu.turns.motorcycles:7687/s","https://yode.bytes.motorcycles:10288/s","https://huen.turns.motorcycles:6237/s","https://itoq.turns.motorcycles:10038/s","https://uhww.purposes-blink.cc:3531/s","https://kkqr.purposes-blink.cc:2441/s","https://danl.purposes-blink.cc:6567/s","https://vyto.bytes.motorcycles:5603/s","https://tweo.purposes-blink.cc:5634/s","https://oupn.turns.motorcycles:3634/s","https://ioet.plugins.pics:7464/s","https://ecom.dealt.cc:1050/s","https://kpjq.assuming.cc:9062/s","https://gflf.bytes.motorcycles:8376/s","https://dczm.dealt.cc:6920/s","https://fqpg.assuming.cc:10874/s","https://hked.purposes-blink.cc:2426/s","https://dmvz.fraud.pics:5454/s","https://hblj.turns.motorcycles:7285/s","https://fuqp.quote-dayton.xyz:7405/s","https://ybzv.purposes-blink.cc:5276/s","https://rndo.assuming.cc:7483/s","https://vtvo.purposes-blink.cc:7151/s","https://xfep.triangle.pics:7963/s","https://oqcu.purposes-blink.cc:4257/s","https://sgla.assuming.cc:7884/s","https://pasr.turns.motorcycles:3783/s","https://uwzo.assuming.cc:8943/s","https://sqya.plugins.pics:3758/s","https://qyqw.plugins.pics:2872/s","https://leav.fraud.pics:10730/s","https://hrwg.quote-dayton.xyz:1096/s","https://qgyh.turns.motorcycles:10674/s","https://xmwo.bytes.motorcycles:5360/s"],"t":1670282523183,"mirrors":["https://bitbucket.org/the7c/update/raw/master/edge/pub/data.json","https://raw.githubusercontent.com/the7c/update/master/master/ui/data.json"]}}