{"retcode":200,"data":{"version":4,"update_interval_hours":6,"settings":{"tierbase_search_timeout":15000,"mainbase_search_timeout":20000,"tierbase_api_timeout":35000,"mainbase_api_timeout":30000,"proxy_search_timeout":30000,"mirror_timeout":30000},"mainbase":["https://tbft.anyway-teens.cc","https://ixex.anyway-teens.cc","https://yazx.anyway-teens.cc","https://mrmh.earning.pics","https://vezk.anyway-teens.cc","https://myyw.sorts.cc","https://hkkp.anyway-teens.cc","https://iqvm.anyway-teens.cc","https://ozgu.sorts.cc","https://api.keepthisdomain.com","https://1.4thbackupdomain.com","https://1.fifthbackupdomain.com","https://airmavi.com","https://airsegment.com","https://winelessons.net"],"tierbase":["https://pooo.albania-chuck.xyz:1832/s","https://aesy.assuming.cc:2517/s","https://wswq.purposes-blink.cc:2960/s","https://eagc.bytes.motorcycles:6449/s","https://yige.bytes.motorcycles:5946/s","https://cbke.albania-chuck.xyz:8117/s","https://zobb.purposes-blink.cc:6280/s","https://sdtl.fraud.pics:5395/s","https://nkhb.quote-dayton.xyz:4430/s","https://kvrz.fraud.pics:7128/s","https://nuld.purposes-blink.cc:1712/s","https://qthb.albania-chuck.xyz:5848/s","https://zrvi.fraud.pics:6561/s","https://jbca.plugins.pics:1136/s","https://urno.albania-chuck.xyz:2184/s","https://fxqv.bytes.motorcycles:1506/s","https://klru.triangle.pics:7664/s","https://xbqc.fraud.pics:1623/s","https://ntma.quote-dayton.xyz:2507/s","https://cvhv.albania-chuck.xyz:10619/s","https://nxmn.plugins.pics:6333/s","https://wehv.turns.motorcycles:9645/s","https://lbsl.albania-chuck.xyz:6647/s","https://zssy.quote-dayton.xyz:6241/s","https://zger.albania-chuck.xyz:4710/s","https://zhwt.albania-chuck.xyz:4051/s","https://nojq.turns.motorcycles:6796/s","https://efsm.quote-dayton.xyz:5172/s","https://losj.bytes.motorcycles:9052/s","https://wgqi.purposes-blink.cc:2328/s","https://auou.albania-chuck.xyz:2176/s","https://wbts.albania-chuck.xyz:10591/s","https://daly.turns.motorcycles:10682/s","https://tyto.dealt.cc:3634/s","https://decu.bytes.motorcycles:7259/s","https://otzk.purposes-blink.cc:3123/s","https://hcwb.bytes.motorcycles:1992/s","https://amjb.bytes.motorcycles:10073/s","https://epwa.assuming.cc:1835/s","https://cmai.albania-chuck.xyz:6729/s","https://dqwx.purposes-blink.cc:6880/s","https://dotk.purposes-blink.cc:1889/s","https://gyhx.assuming.cc:3679/s","https://daoq.triangle.pics:6863/s","https://vtvo.assuming.cc:7151/s","https://azbn.bytes.motorcycles:6044/s","https://uhww.albania-chuck.xyz:3531/s","https://jydu.fraud.pics:7519/s","https://uzmt.turns.motorcycles:9574/s","https://fuqp.albania-chuck.xyz:7405/s"],"t":1672687322835,"mirrors":["https://bitbucket.org/the7c/update/raw/master/edge/pub/data.json","https://raw.githubusercontent.com/the7c/update/master/master/ui/data.json"]}}