{"retcode":200,"data":{"version":4,"update_interval_hours":24,"settings":{"tierbase_search_timeout":15000,"mainbase_search_timeout":20000,"tierbase_api_timeout":35000,"mainbase_api_timeout":30000,"proxy_search_timeout":30000,"mirror_timeout":30000},"mainbase":["https://hkkp.burden-chris.cc","https://tbft.anyway-teens.cc","https://myyw.spare.pics","https://mrmh.burden-chris.cc","https://ozgu.sparc.pics","https://yazx.anyway-teens.cc","https://iqvm.burden-chris.cc","https://vezk.anyway-teens.cc","https://ixex.burden-chris.cc","https://api.keepthisdomain.com","https://1.4thbackupdomain.com","https://1.fifthbackupdomain.com","https://airmavi.com","https://airsegment.com","https://winelessons.net"],"tierbase":["https://euuf.quote-dayton.xyz:3505/s","https://uzmt.triangle.pics:9574/s","https://vztt.turns.motorcycles:7746/s","https://nsas.fraud.pics:9681/s","https://qahe.turns.motorcycles:3881/s","https://bcre.quote-dayton.xyz:8125/s","https://ikxn.plugins.pics:4838/s","https://qcal.turns.motorcycles:2392/s","https://ksae.bytes.motorcycles:6890/s","https://xlve.assuming.cc:5653/s","https://aipi.assuming.cc:7334/s","https://ublg.purposes-blink.cc:10319/s","https://gnbu.purposes-blink.cc:3354/s","https://qrpa.purposes-blink.cc:6230/s","https://ssht.purposes-blink.cc:5902/s","https://sjxx.triangle.pics:7332/s","https://kynr.triangle.pics:6413/s","https://tweo.bytes.motorcycles:5634/s","https://cbke.purposes-blink.cc:8117/s","https://rkmj.bytes.motorcycles:9320/s","https://cddg.triangle.pics:1729/s","https://ybzv.purposes-blink.cc:5276/s","https://pgpf.purposes-blink.cc:9728/s","https://vbdg.quote-dayton.xyz:8691/s","https://elbn.plugins.pics:3249/s","https://azbn.purposes-blink.cc:6044/s","https://qgyh.plugins.pics:10674/s","https://drpg.plugins.pics:10640/s","https://koiq.purposes-blink.cc:5769/s","https://uujh.turns.motorcycles:7314/s","https://ezlt.turns.motorcycles:8982/s","https://cjpn.triangle.pics:2079/s","https://jzci.turns.motorcycles:1210/s","https://qthb.fraud.pics:5848/s","https://pqwi.quote-dayton.xyz:5383/s","https://dczm.purposes-blink.cc:6920/s","https://gcll.purposes-blink.cc:8618/s","https://ibjw.fraud.pics:6885/s","https://kkqr.quote-dayton.xyz:2441/s","https://extw.assuming.cc:1344/s","https://uonk.dealt.cc:7793/s","https://clvk.turns.motorcycles:11021/s","https://fxqv.plugins.pics:1506/s","https://dmvz.purposes-blink.cc:5454/s","https://peir.purposes-blink.cc:10078/s","https://tyto.bytes.motorcycles:3634/s","https://yige.dealt.cc:5946/s","https://umfe.purposes-blink.cc:3013/s","https://ulam.turns.motorcycles:9738/s","https://ghte.dealt.cc:10242/s"],"t":1670346123750,"mirrors":["https://bitbucket.org/the7c/update/raw/master/edge/pub/data.json","https://raw.githubusercontent.com/the7c/update/master/master/ui/data.json"]}}