{"retcode":200,"data":{"version":4,"update_interval_hours":24,"settings":{"tierbase_search_timeout":15000,"mainbase_search_timeout":20000,"tierbase_api_timeout":35000,"mainbase_api_timeout":30000,"proxy_search_timeout":30000,"mirror_timeout":30000},"mainbase":["https://tbft.wants.pics","https://vezk.spare.pics","https://iqvm.earning.pics","https://zrny.produces.cc","https://zonu.tomato-threats.cc","https://hkkp.capitol-flesh.net","https://srpx.medium-auburn.net","https://qlbm.believe-venues.net","https://mrmh.delete-herself.org","https://irch.pupils-savings.org","https://ygbd.layout-tokyo.net","https://hrof.skirt-bargain.net","https://api.keepthisdomain.com","https://1.4thbackupdomain.com","https://1.fifthbackupdomain.com"],"tierbase":["https://ctjv.wilson-kills.net","https://ozgu.trans-jerry.org","https://iejg.filed-prize.org","https://frwy.figured-pieces.org","https://myyw.brings-meters.org","https://qcal.dealt.cc:2392/s","https://dtes.dealt.cc:6555/s","https://tnlq.fraud.pics:10496/s","https://sftz.dealt.cc:1702/s","https://nxmn.fraud.pics:6333/s","https://aywr.fraud.pics:9484/s","https://umfe.router.pics:3013/s","https://flny.router.pics:2244/s","https://pjpm.dealt.cc:9891/s","https://jjgm.fraud.pics:8272/s","https://whfw.fraud.pics:4602/s","https://exda.fraud.pics:9346/s","https://rcob.fraud.pics:4149/s","https://vztt.router.pics:7746/s","https://flra.dealt.cc:4055/s","https://atmq.dealt.cc:8400/s","https://buhr.dealt.cc:8905/s","https://ecks.dealt.cc:2113/s","https://dbob.dealt.cc:9983/s","https://yode.router.pics:10288/s","https://cmai.fraud.pics:6729/s","https://uzmt.fraud.pics:9574/s","https://kjtv.fraud.pics:8799/s","https://taqj.router.pics:9054/s","https://ksdm.router.pics:11023/s","https://teny.fraud.pics:1272/s","https://dobs.dealt.cc:3743/s","https://bcre.fraud.pics:8125/s","https://yoyr.router.pics:9717/s","https://vfsf.router.pics:4789/s","https://luei.dealt.cc:6914/s","https://fofz.fraud.pics:4539/s","https://aipi.router.pics:7334/s","https://jkwb.dealt.cc:1408/s","https://gpio.dealt.cc:10010/s","https://eorf.fraud.pics:4720/s","https://eehu.router.pics:9315/s","https://clvk.fraud.pics:11021/s","https://wlwy.fraud.pics:5849/s","https://dkfj.fraud.pics:4121/s","https://otzk.fraud.pics:3123/s","https://fuqp.fraud.pics:7405/s","https://mrft.fraud.pics:1754/s","https://keny.fraud.pics:4458/s","https://uwzo.fraud.pics:8943/s"],"t":1667131204234,"mirrors":["https://raw.githubusercontent.com/the7c/update/master/master/ui/data.json"]}}