{"retcode":200,"data":{"version":4,"update_interval_hours":24,"settings":{"tierbase_search_timeout":15000,"mainbase_search_timeout":20000,"tierbase_api_timeout":35000,"mainbase_api_timeout":30000,"proxy_search_timeout":30000,"mirror_timeout":30000},"mainbase":["https://govz.sparc.pics","https://tbft.produces.cc","https://ozgu.produces.cc","https://hkkp.dishes.cc","https://hrof.dishes.cc","https://mrmh.capitol-flesh.net","https://myyw.sparc.pics","https://iqvm.spare.pics","https://vezk.table-harris.xyz","https://ixex.table-harris.xyz","https://ctjv.sparc.pics","https://irch.table-harris.xyz","https://api.keepthisdomain.com","https://1.4thbackupdomain.com","https://1.fifthbackupdomain.com"],"tierbase":["https://yazx.spare.pics","https://wmdi.quote-dayton.xyz:5849/s","https://qaik.bytes.motorcycles:9371/s","https://luei.bytes.motorcycles:6914/s","https://aesy.quote-dayton.xyz:2517/s","https://losj.quote-dayton.xyz:9052/s","https://jkwb.plugins.pics:1408/s","https://efsm.quote-dayton.xyz:5172/s","https://mrft.fraud.pics:1754/s","https://yveb.bytes.motorcycles:10994/s","https://ldvp.triangle.pics:10873/s","https://clvk.triangle.pics:11021/s","https://xshh.plugins.pics:3695/s","https://eetf.bytes.motorcycles:9219/s","https://mbxu.assuming.cc:10275/s","https://asmu.bytes.motorcycles:6770/s","https://vztt.assuming.cc:7746/s","https://wssh.bytes.motorcycles:2595/s","https://yslx.assuming.cc:1721/s","https://qjfb.bytes.motorcycles:1490/s","https://bphj.assuming.cc:3593/s","https://xmyh.bytes.motorcycles:4599/s","https://obhz.dealt.cc:10546/s","https://dvwg.assuming.cc:6738/s","https://jbca.quote-dayton.xyz:6615/s","https://qvpp.dealt.cc:5657/s","https://zrvi.assuming.cc:6561/s","https://sftz.quote-dayton.xyz:9260/s","https://elbn.assuming.cc:3249/s","https://coym.assuming.cc:9552/s","https://lpjs.plugins.pics:2628/s","https://jhac.bytes.motorcycles:7254/s","https://elhu.fraud.pics:4763/s","https://jzci.dealt.cc:1210/s","https://dbwg.quote-dayton.xyz:9124/s","https://tbsd.bytes.motorcycles:6892/s","https://azbn.plugins.pics:6044/s","https://vtue.bytes.motorcycles:8676/s","https://dtes.quote-dayton.xyz:6555/s","https://wlwy.quote-dayton.xyz:5849/s","https://hrwg.bytes.motorcycles:1096/s","https://eehu.router.pics:9315/s","https://cyxh.fraud.pics:1519/s","https://euuf.assuming.cc:3505/s","https://aipi.triangle.pics:7334/s","https://hzus.assuming.cc:7491/s","https://exda.bytes.motorcycles:9346/s","https://wjeu.bytes.motorcycles:9064/s","https://uysc.triangle.pics:10113/s","https://xblm.quote-dayton.xyz:1269/s"],"t":1668517203680,"mirrors":["https://bitbucket.org/the7c/update/raw/master/edge/pub/data.json","https://raw.githubusercontent.com/the7c/update/master/master/ui/data.json"]}}