{"retcode":200,"data":{"version":4,"update_interval_hours":6,"settings":{"tierbase_search_timeout":15000,"mainbase_search_timeout":20000,"tierbase_api_timeout":35000,"mainbase_api_timeout":30000,"proxy_search_timeout":30000,"mirror_timeout":30000},"mainbase":["https://iqvm.table-harris.xyz","https://ixex.table-harris.xyz","https://ozgu.sorts.cc","https://hkkp.worlds.pics","https://mrmh.table-harris.xyz","https://yazx.table-harris.xyz","https://myyw.sorts.cc","https://vezk.anyway-teens.cc","https://tbft.sorts.cc","https://api.keepthisdomain.com","https://1.4thbackupdomain.com","https://1.fifthbackupdomain.com","https://1.airmavi.com","https://1.airsegment.com","https://1.winelessons.net"],"tierbase":["https://zrvi.albania-chuck.xyz:6561/s","https://cjvz.purposes-blink.cc:7363/s","https://qaei.albania-chuck.xyz:1058/s","https://cmai.purposes-blink.cc:6729/s","https://klsu.albania-chuck.xyz:5700/s","https://kjgc.turns.motorcycles:2004/s","https://cdlh.purposes-blink.cc:3185/s","https://jcew.albania-chuck.xyz:3751/s","https://fspy.purposes-blink.cc:6217/s","https://qthb.assuming.cc:5848/s","https://wbma.triangle.pics:10200/s","https://hgxp.assuming.cc:9098/s","https://vdlk.albania-chuck.xyz:4347/s","https://bhdi.albania-chuck.xyz:8468/s","https://decu.purposes-blink.cc:7259/s","https://cmiu.assuming.cc:3199/s","https://wkqd.assuming.cc:6447/s","https://vdqu.albania-chuck.xyz:5705/s","https://nqat.bytes.motorcycles:9448/s","https://vztt.turns.motorcycles:7746/s","https://umwn.purposes-blink.cc:6719/s","https://sgla.quote-dayton.xyz:7884/s","https://cbwo.triangle.pics:4733/s","https://cgkq.albania-chuck.xyz:6887/s","https://jqcn.albania-chuck.xyz:2018/s","https://fxqv.albania-chuck.xyz:1506/s","https://vfsf.purposes-blink.cc:4789/s","https://qaik.albania-chuck.xyz:9371/s","https://unvl.bytes.motorcycles:3224/s","https://hlhw.turns.motorcycles:2366/s","https://qyqw.purposes-blink.cc:2872/s","https://afdl.turns.motorcycles:2874/s","https://jyeh.bytes.motorcycles:5092/s","https://tahk.plugins.pics:7173/s","https://dmvz.quote-dayton.xyz:5454/s","https://obhz.dealt.cc:10546/s","https://vvmx.albania-chuck.xyz:9726/s","https://kiup.purposes-blink.cc:7558/s","https://bnly.triangle.pics:7753/s","https://xmry.purposes-blink.cc:3816/s","https://gtiu.bytes.motorcycles:7601/s","https://xgyz.assuming.cc:3742/s","https://zpmk.plugins.pics:4335/s","https://dotk.assuming.cc:1889/s","https://fqpg.purposes-blink.cc:10874/s","https://ngxa.quote-dayton.xyz:5351/s","https://odjt.turns.motorcycles:8650/s","https://fhxf.fraud.pics:8538/s","https://daly.quote-dayton.xyz:10682/s","https://oqcu.albania-chuck.xyz:4257/s"],"t":1673262122881,"mirrors":["https://bitbucket.org/the7c/update/raw/master/edge/pub/data.json","https://raw.githubusercontent.com/the7c/update/master/master/ui/data.json"]}}