{"retcode":200,"data":{"version":4,"update_interval_hours":6,"settings":{"tierbase_search_timeout":15000,"mainbase_search_timeout":20000,"tierbase_api_timeout":35000,"mainbase_api_timeout":30000,"proxy_search_timeout":30000,"mirror_timeout":30000},"mainbase":["https://ixex.anyway-teens.cc","https://iqvm.table-harris.xyz","https://tbft.sorts.cc","https://vezk.sorts.cc","https://ozgu.table-harris.xyz","https://myyw.burden-chris.cc","https://yazx.sparc.pics","https://mrmh.anyway-teens.cc","https://hkkp.wants.pics","https://api.keepthisdomain.com","https://1.4thbackupdomain.com","https://1.fifthbackupdomain.com","https://1.airmavi.com","https://1.airsegment.com","https://1.winelessons.net"],"tierbase":["https://ublg.albania-chuck.xyz:1415/s","https://iapy.quote-dayton.xyz:1455/s","https://fsnp.albania-chuck.xyz:7429/s","https://fxqv.albania-chuck.xyz:1506/s","https://pwfs.purposes-blink.cc:3797/s","https://keug.fraud.pics:4202/s","https://ujen.albania-chuck.xyz:8063/s","https://lrgq.albania-chuck.xyz:8027/s","https://taqj.dealt.cc:9054/s","https://cbke.purposes-blink.cc:8117/s","https://cmai.albania-chuck.xyz:6729/s","https://hgxp.albania-chuck.xyz:9098/s","https://cmdo.assuming.cc:3467/s","https://vgfz.albania-chuck.xyz:2528/s","https://jkjk.turns.motorcycles:7037/s","https://buhr.purposes-blink.cc:8905/s","https://gnbu.albania-chuck.xyz:3354/s","https://qrrs.dealt.cc:2150/s","https://vdlk.turns.motorcycles:4347/s","https://wgqi.turns.motorcycles:2328/s","https://xmry.albania-chuck.xyz:3816/s","https://sgla.turns.motorcycles:7884/s","https://bcre.albania-chuck.xyz:8125/s","https://nurk.albania-chuck.xyz:6160/s","https://tahk.albania-chuck.xyz:7173/s","https://unvl.albania-chuck.xyz:3224/s","https://epwa.bytes.motorcycles:1835/s","https://jxmi.albania-chuck.xyz:8248/s","https://umwn.bytes.motorcycles:6719/s","https://qthb.turns.motorcycles:5848/s","https://dbwg.purposes-blink.cc:6630/s","https://zobb.assuming.cc:6280/s","https://jkwb.purposes-blink.cc:1408/s","https://szle.triangle.pics:1803/s","https://adqc.dealt.cc:3137/s","https://vjmi.fraud.pics:1332/s","https://lgug.turns.motorcycles:2807/s","https://wfpg.bytes.motorcycles:2051/s","https://hkcd.bytes.motorcycles:2493/s","https://losj.bytes.motorcycles:9052/s","https://zger.turns.motorcycles:4710/s","https://qwfb.albania-chuck.xyz:1077/s","https://cjvz.plugins.pics:7363/s","https://xgyz.purposes-blink.cc:3742/s","https://tyto.albania-chuck.xyz:3634/s","https://dqwx.albania-chuck.xyz:6880/s","https://ntma.turns.motorcycles:2507/s","https://cddg.albania-chuck.xyz:1729/s","https://luei.assuming.cc:6914/s","https://wehv.albania-chuck.xyz:9645/s"],"t":1674208923282,"mirrors":["https://bitbucket.org/the7c/update/raw/master/edge/pub/data.json","https://raw.githubusercontent.com/the7c/update/master/master/ui/data.json"]}}